AE/verilog/automi/string/abba/abba.sv
module abba (output z, input [1:2]x, input clock);

  wire [1:2]out_reg;
  wire [1:2]in_reg;

  register r(out_reg, clock, 1'b1, in_reg);
  sigma sm(in_reg, out_reg, x);
  omega om(z, out_reg, x);

endmodule // abba

module omega (output z, input [1:2]s, input [1:2]x);

  assign
    z = s[1] & ~s[2] & ~x[1] & ~x[2];

endmodule // omega

module sigma (output [1:2]ns, input [1:2]s, input [1:2]x);

  assign
    ns[1] = s[2] & ~x[1] & x[2];
  assign
    ns[2] = ~s[1] &  s[2] & ~x[1]
          | ~s[1] & ~x[2]
          |  s[2] & ~x[2];

endmodule // sigma

module register (output reg [1:N]state, input clock, input enable, input [1:N]val);

  parameter N = 2;

  // Viene eseguito quando il modulo viene istanziato
  initial begin
    state = 0;
  end

  // Viene eseguito ad ogni posedge del clock
  always @ (posedge clock) begin
    if (enable)
      state <= val; // '<=': Assegnamento asincrono (Piu' assegnamenti asincroni consecutivi vengono eseguiti contemporaneamente)
  end

endmodule // register

AE/verilog/automi/string/abba/test_abba.sv
module test_abba();

  reg [1:2] x;
  reg       clock;

  wire z;

  abba test(z, x, clock);
  initial clock = 0;

  always begin
    #2 clock = 1;
    #1 clock = 0;
  end

  initial begin
    $dumpfile("abba.vcd");
    $dumpvars;

    x = 2'b00;

    #4
    x = 2'b01;

    #5
    x = 2'b01;

    #1
    x = 2'b00;

    #10
    $finish;

  end
endmodule // test_abba

AE/verilog/automi/string/abba/abba.vcd
$date
	Tue Oct  8 15:37:40 2019
$end
$version
	Icarus Verilog
$end
$timescale
	1s
$end
$scope module test_abba $end
$var wire 1 ! z $end
$var reg 1 " clock $end
$var reg 2 # x [1:2] $end
$scope module test $end
$var wire 1 " clock $end
$var wire 2 $ x [1:2] $end
$var wire 1 ! z $end
$var wire 2 % out_reg [1:2] $end
$var wire 2 & in_reg [1:2] $end
$scope module om $end
$var wire 2 ' x [1:2] $end
$var wire 1 ! z $end
$var wire 2 ( s [1:2] $end
$upscope $end
$scope module r $end
$var wire 1 " clock $end
$var wire 1 ) enable $end
$var wire 2 * val [1:2] $end
$var reg 2 + state [1:2] $end
$upscope $end
$scope module sm $end
$var wire 2 , s [1:2] $end
$var wire 2 - x [1:2] $end
$var wire 2 . ns [1:2] $end
$upscope $end
$upscope $end
$upscope $end
$enddefinitions $end
#0
$dumpvars
b1 .
b0 -
b0 ,
b0 +
b1 *
1)
b0 (
b0 '
b1 &
b0 %
b0 $
b0 #
0"
0!
$end
#2
b1 %
b1 (
b1 +
b1 ,
1"
#3
0"
#4
b11 &
b11 *
b11 .
b1 #
b1 $
b1 '
b1 -
#5
b10 &
b10 *
b10 .
b11 %
b11 (
b11 +
b11 ,
1"
#6
0"
#8
b0 &
b0 *
b0 .
b10 %
b10 (
b10 +
b10 ,
1"
#9
0"
#10
1!
b0 #
b0 $
b0 '
b0 -
#11
b1 &
b1 *
b1 .
0!
b0 %
b0 (
b0 +
b0 ,
1"
#12
0"
#14
b1 %
b1 (
b1 +
b1 ,
1"
